get_response/__init__.py
get_response/base_parser.py
get_response/interface.py
get_response/json_parser.py
get_response/soap_parser.py
get_response-0.1.2.dist-info/LICENSE
get_response-0.1.2.dist-info/METADATA
get_response-0.1.2.dist-info/WHEEL
get_response-0.1.2.dist-info/top_level.txt
get_response-0.1.2.dist-info/RECORD
