Metadata-Version: 2.1
Name: get-response
Version: 0.1.2
Summary: Parsing Tool for json-like, xml-like and etc Types of Responsefor Humans.
Home-page: https://github.com/skv0zsneg/get-response
Author: skv0zsneg
License: UNKNOWN
Project-URL: Bug Tracker, https://github.com/skv0zsneg/get-response/issues
Platform: UNKNOWN
Classifier: Programming Language :: Python :: 3
Classifier: License :: OSI Approved :: MIT License
Classifier: Operating System :: OS Independent
Requires-Python: >=3.8
